discoverdollar_name_match/__init__.py
discoverdollar_name_match-0.0.1.dist-info/LICENSE
discoverdollar_name_match-0.0.1.dist-info/METADATA
discoverdollar_name_match-0.0.1.dist-info/WHEEL
discoverdollar_name_match-0.0.1.dist-info/top_level.txt
discoverdollar_name_match-0.0.1.dist-info/RECORD
